odoo/addons/sale_stock_line_sequence/README.rst
odoo/addons/sale_stock_line_sequence/__init__.py
odoo/addons/sale_stock_line_sequence/__manifest__.py
odoo/addons/sale_stock_line_sequence/i18n/es.po
odoo/addons/sale_stock_line_sequence/i18n/it.po
odoo/addons/sale_stock_line_sequence/i18n/sale_stock_line_sequence.pot
odoo/addons/sale_stock_line_sequence/models/__init__.py
odoo/addons/sale_stock_line_sequence/models/sale_order.py
odoo/addons/sale_stock_line_sequence/models/stock_move.py
odoo/addons/sale_stock_line_sequence/readme/CONTRIBUTORS.md
odoo/addons/sale_stock_line_sequence/readme/DESCRIPTION.md
odoo/addons/sale_stock_line_sequence/static/description/icon.png
odoo/addons/sale_stock_line_sequence/static/description/index.html
odoo/addons/sale_stock_line_sequence/tests/__init__.py
odoo/addons/sale_stock_line_sequence/tests/test_line_sequence.py
odoo_addon_sale_stock_line_sequence-18.0.1.0.0.2.dist-info/METADATA
odoo_addon_sale_stock_line_sequence-18.0.1.0.0.2.dist-info/WHEEL
odoo_addon_sale_stock_line_sequence-18.0.1.0.0.2.dist-info/top_level.txt
odoo_addon_sale_stock_line_sequence-18.0.1.0.0.2.dist-info/RECORD
