Metadata-Version: 2.1
Name: odoo-addon-sale_stock_line_sequence
Version: 18.0.1.0.0.2
Requires-Python: >=3.10
Requires-Dist: odoo-addon-sale_order_line_sequence==18.0.*
Requires-Dist: odoo-addon-stock_picking_line_sequence==18.0.*
Requires-Dist: odoo==18.0.*
Summary: Glue Module for Sale Order Line Sequence and Stock Picking Line Sequence
Home-page: https://github.com/OCA/sale-workflow
License: AGPL-3
Author: ForgeFlow, Odoo Community Association (OCA)
Author-email: support@odoo-community.org
Classifier: Programming Language :: Python
Classifier: Framework :: Odoo
Classifier: Framework :: Odoo :: 18.0
Classifier: License :: OSI Approved :: GNU Affero General Public License v3
